{
  "login": "Iniciar sesión",
  "signup": "Regístrate",
  "email": "Correo electrónico:",
  "password": "Contraseña:",
  "username": "Usuario:",
  "re-enterpassword": "Repite contraseña:",
  "continue": "Continuar",
  "forgot-password": "¿Has olvidado tu contraseña?",
  "newuser?": "¿Nuevo usuario? Registrate aquí.",
  "email-verification": "Te hemos enviado un código de verificación a tu correo",
  "change-password": "Cambiar contraseña",
  "email-recover": "Te hemos enviado un código de recuperación a tu correo",
  "password-reset": "Recupera tu contraseña",
  "welcome": "Bienvenido.",

  "myprofile": "Mi perfil",
  "myoffers": "Mis ofertas",
  "signout": "Cerrar sesión ",
  "settings": "Ajustes",
  "theme": "Tema",
  "language": "Idioma",

  "all-offers": "Todas las ofertas",
  "todays-offers": "Ofertas del día",
  "most-rated-offers": "Ofertas más valoradas",
  "favorite-offers": "Ofertas favoritas",

  "link": "Enlace:",
  "title": "Título:",
  "description": "Descripción:",
  "offerprice": "Precio de oferta:",
  "originalprice": "Precio original:",
  "platform": "Plataforma:",
  "expiration-date": "Fecha de caducidad:",
  "deleteoffer": "Borrar oferta",
  "send-vote-success": "Tu voto se ha registrado correctamente",

  "upload-image": "Haz que tu oferta destaque añadiendo una imagen",
  "upload-without-image": " Subir oferta sin imagen",
  "offeruploaded": "La oferta se ha subido correctamente",

  "modify-offer-confirmation": "¿Estás seguro que quieres modificar esta oferta?",
  "delete-offer-confirmation": "¿Estás seguro que quieres borrar esta oferta?",
  "image-change-success": "La imagen se ha modificado correctamente",
  "link-change-success": "El enlace se ha modificado correctamente",
  "title-change-success": "El título se ha modificado correctamente",
  "description-change-success": "La descripción se ha modificado correctamente",
  "offerprice-change-success": "El precio de la oferta se ha modificado correctamente",
  "originalprice-change-success": " El precio original se ha modificado correctamente",
  "platform-change-success": "La plataforma se ha modificado correctamente",
  "expiration-change-success": "La fecha de vencimiento se ha modificado correctamente",
  "offer-deleted-success": "Tu oferta se ha eliminado correctamente",

  "expired-offer": "Oferta caducada",
  "link-to-offer": "Ir a la oferta",
  "send": "Enviar",

  "comment-delete?": "¿Estás seguro que quieres eliminar este comentario?",
  "yes": "Sí",
  "no": "No",
  "comment-delete-success": "Tu comentario se ha eliminado correctamente",

  "member-since": "Miembre desde",
  "privacy": "Privacidad",
  "delete-account": "Borrar cuenta",

  "currentpassword": "Contraseña actual",
  "newpassword": "Nueva contraseña",
  "user-delete-confirmation": "¿Estás seguro que quieres borrar tu usuario?",
  "user-modify-confirmation": "¿Estás seguro que quieres modificar tu usuario?",
  "user-modify-success": " Tu usuario se ha modificado correctamente",
  "user-delete-success": "Tu usuario ha sido eliminado",
  "avatar-modify-success": "Tu avatar se ha modificado correctamente",
  "password-reset-confirmation": "Tu contreseña se ha modificado correctamente",

  "oops": "Ups!, Algo ha salido mal",
  "page-notfound": "La página web no se ha encontrado",
  "fail-connection": "Fallo de conexión con el servidor",
  "home": "Volver al inicio",

  "about-us": "Sobre nosotros",
  "ourpage": "Conócenos",
  "legal": "Legal",
  "legaladvice": "Aviso Legal",
  "followus": "Síguenos",

  "password-match": "Las contraseñas no conciden",
  "password-user-match": "La contraseña no puede ser igual al nombre de usuario",
  "password-8char-error": "La longitud de la contraseña debe ser de al menos 8 caracteres",
  "password-20char-error": "La longitud de la contraseña debe ser menor o igual a 20 caracteres",
  "password-white-spaces-error": "La contraseña no debe contener espacios en blanco",
  "password-specialChar-error": "La contraseña debe contener al menos 1 caracter especial",
  "password-uppercaseChar-error": "La contraseña debe contener al menos 1 caracter en mayúscula",
  "password-numChar-error": "La contraseña debe contener al menos 1 carácter numérico",
  "username-4char-error": "La longitud del usuario debe tener al menos 4 caracteres",
  "username-15char-error": "La longitud del usuario debe ser inferior o igual a 15 caracteres",
  "post-comment-error": "El comentario no puede superar los 170 caracteres",
  "email-password-error": "Email o contraseña incorrectos",
  "verify-error": "Usuario no verificado",
  "url-280char-error": "La longitud de la URL debe ser inferior o igual a 280 caracteres",
  "title-30char-error": "La longitud del título debe ser inferior o igual a 30 caracteres",
  "descrip-280char-error": "La longitud de la descripción debe ser inferior o igual a 280 caracteres",
  "offer_price-positive-error": "El precio de oferta debe ser un número positivo",
  "price-positive-error": "El precio original debe ser un número positivo",
  "expire-error": "La fecha de caducidad no puede ser anterior a hoy",
  "no-permissions-error": "No tienes permisos para modificar este usuario",
  "same-password-error": "La nueva contraseña es igual a la anterior",
  "no-image-error": "No has seleccionado ninguna imagen",
  "vote-own-offer-error": "No puedes votar tu propia oferta",
  "vote-already-offer-error": "No puedes votar dos veces la misma oferta"
}
